{
	"cmake" : 
	{
		"generator" : 
		{
			"multiConfig" : false,
			"name" : "Ninja"
		},
		"paths" : 
		{
			"cmake" : "/home/tasnim/.local/share/JetBrains/Toolbox/apps/clion/bin/cmake/linux/x64/bin/cmake",
			"cpack" : "/home/tasnim/.local/share/JetBrains/Toolbox/apps/clion/bin/cmake/linux/x64/bin/cpack",
			"ctest" : "/home/tasnim/.local/share/JetBrains/Toolbox/apps/clion/bin/cmake/linux/x64/bin/ctest",
			"root" : "/home/tasnim/.local/share/JetBrains/Toolbox/apps/clion/bin/cmake/linux/x64/share/cmake-3.27"
		},
		"version" : 
		{
			"isDirty" : false,
			"major" : 3,
			"minor" : 27,
			"patch" : 8,
			"string" : "3.27.8",
			"suffix" : ""
		}
	},
	"objects" : 
	[
		{
			"jsonFile" : "codemodel-v2-2f6818e8850e2fe2060e.json",
			"kind" : "codemodel",
			"version" : 
			{
				"major" : 2,
				"minor" : 6
			}
		},
		{
			"jsonFile" : "cache-v2-d21e1e4d1fdf04b3d540.json",
			"kind" : "cache",
			"version" : 
			{
				"major" : 2,
				"minor" : 0
			}
		},
		{
			"jsonFile" : "cmakeFiles-v1-a31379689d92313270d6.json",
			"kind" : "cmakeFiles",
			"version" : 
			{
				"major" : 1,
				"minor" : 0
			}
		},
		{
			"jsonFile" : "toolchains-v1-dba85a7694ae4b2e7d3f.json",
			"kind" : "toolchains",
			"version" : 
			{
				"major" : 1,
				"minor" : 0
			}
		}
	],
	"reply" : 
	{
		"cache-v2" : 
		{
			"jsonFile" : "cache-v2-d21e1e4d1fdf04b3d540.json",
			"kind" : "cache",
			"version" : 
			{
				"major" : 2,
				"minor" : 0
			}
		},
		"cmakeFiles-v1" : 
		{
			"jsonFile" : "cmakeFiles-v1-a31379689d92313270d6.json",
			"kind" : "cmakeFiles",
			"version" : 
			{
				"major" : 1,
				"minor" : 0
			}
		},
		"codemodel-v2" : 
		{
			"jsonFile" : "codemodel-v2-2f6818e8850e2fe2060e.json",
			"kind" : "codemodel",
			"version" : 
			{
				"major" : 2,
				"minor" : 6
			}
		},
		"toolchains-v1" : 
		{
			"jsonFile" : "toolchains-v1-dba85a7694ae4b2e7d3f.json",
			"kind" : "toolchains",
			"version" : 
			{
				"major" : 1,
				"minor" : 0
			}
		}
	}
}
